<files>
<file>Parameters/cellResolution001.xml</file>
<file>Parameters/clockMode001.xml</file>
<file>Parameters/clockMode002.xml</file>
<file>Parameters/clockMode003.xml</file>
<file>Parameters/frameRate001.xml</file>
<file>Parameters/frameRate002.xml</file>
<file>Parameters/frameRateMultiplier001.xml</file>
<file>Parameters/markerMode001.xml</file>
<file>Parameters/markerMode002.xml</file>
<file>Parameters/smpteMode001.xml</file>
<file>Parameters/smpteMode002.xml</file>
<file>Parameters/subFrameRate001.xml</file>
<file>Parameters/tickRate001.xml</file>
<file>Parameters/timeBase001.xml</file>
<file>Parameters/timeBase002.xml</file>
<file>Parameters/timeBase003.xml</file>
<file>Content/Br001.xml</file>
<file>Content/Paragraph001.xml</file>
<file>Content/Paragraph002.xml</file>
<file>Content/Paragraph003.xml</file>
<file>Content/Paragraph004.xml</file>
<file>Content/Paragraph005.xml</file>
<file>Content/Span001.xml</file>
<file>Content/Span002.xml</file>
<file>Content/Span003.xml</file>
<file>Content/Span004.xml</file>
<file>Content/Span005.xml</file>
<file>Content/div001.xml</file>
<file>Content/div002.xml</file>
<file>Content/div003.xml</file>
<file>Content/foreign001.xml</file>
<file>Content/tt001.xml</file>
<file>Content/tt002.xml</file>
<file>Content/tt003.xml</file>
<file>Styling/BackgroundColor001.xml</file>
<file>Styling/BackgroundColor002.xml</file>
<file>Styling/BackgroundColor003.xml</file>
<file>Styling/BackgroundColor004.xml</file>
<file>Styling/BackgroundColor005.xml</file>
<file>Styling/BackgroundColor006.xml</file>
<file>Styling/BackgroundColor007.xml</file>
<file>Styling/BackgroundColor008.xml</file>
<file>Styling/BackgroundColor009.xml</file>
<file>Styling/Color001.xml</file>
<file>Styling/Color002.xml</file>
<file>Styling/Color003.xml</file>
<file>Styling/Color004.xml</file>
<file>Styling/Color005.xml</file>
<file>Styling/Color006.xml</file>
<file>Styling/Color007.xml</file>
<file>Styling/Color008.xml</file>
<file>Styling/Color009.xml</file>
<file>Styling/LineHeight001.xml</file>
<file>Styling/LineHeight002.xml</file>
<file>Styling/LineHeight003.xml</file>
<file>Styling/LineHeight004.xml</file>
<file>Styling/Padding001.xml</file>
<file>Styling/Padding002.xml</file>
<file>Styling/Padding003.xml</file>
<file>Styling/Padding004.xml</file>
<file>Styling/Padding005.xml</file>
<file>Styling/Style001.xml</file>
<file>Styling/Styling001.xml</file>
<file>Styling/TextAlign001.xml</file>
<file>Styling/TextAlign002.xml</file>
<file>Styling/TextAlign003.xml</file>
<file>Styling/TextAlign004.xml</file>
<file>Styling/TextAlign005.xml</file>
<file>Styling/TextAlign006.xml</file>
<file>Styling/TextAlign007.xml</file>
<file>Styling/TextAlign008.xml</file>
<file>Styling/TextAlign009.xml</file>
<file>Styling/TextDecoration001.xml</file>
<file>Styling/TextDecoration002.xml</file>
<file>Styling/TextDecoration003.xml</file>
<file>Styling/TextDecoration004.xml</file>
<file>Styling/TextDecoration005.xml</file>
<file>Styling/TextDecoration006.xml</file>
<file>Styling/TextDecoration007.xml</file>
<file>Styling/TextDecoration008.xml</file>
<file>Styling/TextDecoration009.xml</file>
<file>Styling/TextDecoration010.xml</file>
<file>Styling/TextDecoration011.xml</file>
<file>Styling/TextDecoration012.xml</file>
<file>Styling/TextOutline001.xml</file>
<file>Styling/TextOutline002.xml</file>
<file>Styling/TextOutline003.xml</file>
<file>Styling/TextOutline004.xml</file>
<file>Styling/TextOutline005.xml</file>
<file>Styling/TextOutline006.xml</file>
<file>Styling/Visibility001.xml</file>
<file>Styling/Visibility002.xml</file>
<file>Styling/Visibility003.xml</file>
<file>Styling/Visibility004.xml</file>
<file>Timing/BeginDur001.xml</file>
<file>Timing/BeginEnd001.xml</file>
<file>Timing/BeginEnd002.xml</file>
<file>Timing/BeginEnd003.xml</file>
</files>
